[{"code":"ABQ","display":"ABQ - Albuquerque International Sunport","lat":35.039976,"long":-106.608925},{"code":"ADW","display":"ADW - Joint Base Andrews","lat":38.810799,"long":-76.866997},{"code":"ATL","display":"ATL - Hartsfield Jackson Atlanta International Airport","lat":33.6367,"long":-84.428101},{"code":"AUS","display":"AUS - Austin Bergstrom International Airport","lat":30.197535,"long":-97.662015},{"code":"BDL","display":"BDL - Bradley International Airport","lat":41.93851,"long":-72.688066},{"code":"BNA","display":"BNA - Nashville International Airport","lat":36.1245,"long":-86.6782},{"code":"BOS","display":"BOS - Logan International Airport","lat":42.36197,"long":-71.0079},{"code":"BUF","display":"BUF - Buffalo Niagara International Airport","lat":42.940498,"long":-78.732201},{"code":"BWI","display":"BWI - Baltimore/Washington International Thurgood Marshall Airport","lat":39.1754,"long":-76.668297},{"code":"CLE","display":"CLE - Cleveland Hopkins International Airport","lat":41.411701,"long":-81.8498},{"code":"CLT","display":"CLT - Charlotte Douglas International Airport","lat":35.2140007,"long":-80.94309998},{"code":"CMA","display":"CMA - Camarillo International Airport","lat":34.213699,"long":-119.094002},{"code":"CMH","display":"CMH - John Glenn Columbus International Airport","lat":39.998001,"long":-82.891899},{"code":"CVG","display":"CVG - Cincinnati Northern Kentucky International Airport","lat":39.048801,"long":-84.667801},{"code":"DCA","display":"DCA - Ronald Reagan Washington National Airport","lat":38.8521,"long":-77.037697},{"code":"DEN","display":"DEN - Denver International Airport","lat":39.86169815,"long":-104.6729965},{"code":"DFW","display":"DFW - Dallas Fort Worth International Airport","lat":32.896801,"long":-97.038002},{"code":"DTW","display":"DTW - Detroit Metropolitan Wayne County Airport","lat":42.21377,"long":-83.353786},{"code":"EWR","display":"EWR - Newark Liberty International Airport","lat":40.692501,"long":-74.168701},{"code":"FLL","display":"FLL - Fort Lauderdale Hollywood International Airport","lat":26.072599,"long":-80.152702},{"code":"IAD","display":"IAD - Washington Dulles International Airport","lat":38.9445,"long":-77.455803},{"code":"IAH","display":"IAH - George Bush Intercontinental Houston Airport","lat":29.9843998,"long":-95.34140015},{"code":"IND","display":"IND - Indianapolis International Airport","lat":39.7173,"long":-86.294403},{"code":"JAX","display":"JAX - Jacksonville International Airport","lat":30.492469,"long":-81.687813},{"code":"JFK","display":"JFK - John F Kennedy International Airport","lat":40.639447,"long":-73.779317},{"code":"LAS","display":"LAS - Harry Reid International Airport","lat":36.083361,"long":-115.151817},{"code":"LAX","display":"LAX - Los Angeles International Airport","lat":33.942501,"long":-118.407997},{"code":"LGA","display":"LGA - LaGuardia Airport","lat":40.777199,"long":-73.872597},{"code":"MCI","display":"MCI - Kansas City International Airport","lat":39.2976,"long":-94.713898},{"code":"MCO","display":"MCO - Orlando International Airport","lat":28.42939949,"long":-81.30899811},{"code":"MDW","display":"MDW - Chicago Midway International Airport","lat":41.785999,"long":-87.752403},{"code":"MEM","display":"MEM - Memphis International Airport","lat":35.0424,"long":-89.9767},{"code":"MIA","display":"MIA - Miami International Airport","lat":25.79319954,"long":-80.29060364},{"code":"MKE","display":"MKE - General Mitchell International Airport","lat":42.947201,"long":-87.896599},{"code":"MSP","display":"MSP - Minneapolis–Saint Paul International Airport / Wold–Chamberlain Field","lat":44.880081,"long":-93.221741},{"code":"MSY","display":"MSY - Louis Armstrong New Orleans International Airport","lat":29.993401,"long":-90.258003},{"code":"OAK","display":"OAK - San Francisco Bay Oakland International Airport","lat":37.720085,"long":-122.221184},{"code":"OKC","display":"OKC - Will Rogers World Airport","lat":35.393388,"long":-97.598248},{"code":"OMA","display":"OMA - Eppley Airfield","lat":41.3032,"long":-95.894096},{"code":"ONT","display":"ONT - Ontario International Airport","lat":34.056,"long":-117.600998},{"code":"ORD","display":"ORD - Chicago O'Hare International Airport","lat":41.9786,"long":-87.9048},{"code":"ORF","display":"ORF - Norfolk International Airport","lat":36.895341,"long":-76.201},{"code":"PBI","display":"PBI - Palm Beach International Airport","lat":26.683201,"long":-80.095596},{"code":"PDX","display":"PDX - Portland International Airport","lat":45.588699,"long":-122.598},{"code":"PHL","display":"PHL - Philadelphia International Airport","lat":39.871899,"long":-75.241096},{"code":"PHX","display":"PHX - Phoenix Sky Harbor International Airport","lat":33.435302,"long":-112.005905},{"code":"PIT","display":"PIT - Pittsburgh International Airport","lat":40.491501,"long":-80.232903},{"code":"PVD","display":"PVD - Theodore Francis Green State Airport","lat":41.725038,"long":-71.425668},{"code":"PWM","display":"PWM - Portland International Jetport","lat":43.646198,"long":-70.309303},{"code":"RDU","display":"RDU - Raleigh Durham International Airport","lat":35.877602,"long":-78.787498},{"code":"RIC","display":"RIC - Richmond International Airport","lat":37.505199,"long":-77.319702},{"code":"RNO","display":"RNO - Reno Tahoe International Airport","lat":39.4991,"long":-119.767998},{"code":"RSW","display":"RSW - Southwest Florida International Airport","lat":26.53619957,"long":-81.75520325},{"code":"SAN","display":"SAN - San Diego International Airport","lat":32.73360062,"long":-117.1900024},{"code":"SAT","display":"SAT - San Antonio International Airport","lat":29.533701,"long":-98.469803},{"code":"SAV","display":"SAV - Savannah Hilton Head International Airport","lat":32.127602,"long":-81.202103},{"code":"SDF","display":"SDF - Louisville Muhammad Ali International Airport","lat":38.1744,"long":-85.736},{"code":"SEA","display":"SEA - Seattle–Tacoma International Airport","lat":47.447943,"long":-122.310276},{"code":"SFB","display":"SFB - Orlando Sanford International Airport","lat":28.77759933,"long":-81.23750305},{"code":"SFO","display":"SFO - San Francisco International Airport","lat":37.619806,"long":-122.374821},{"code":"SJC","display":"SJC - Norman Y. Mineta San Jose International Airport","lat":37.362452,"long":-121.929188},{"code":"SLC","display":"SLC - Salt Lake City International Airport","lat":40.78886,"long":-111.979866},{"code":"SMF","display":"SMF - Sacramento International Airport","lat":38.6954,"long":-121.591003},{"code":"SNA","display":"SNA - John Wayne Orange County International Airport","lat":33.675701,"long":-117.867996},{"code":"SRQ","display":"SRQ - Sarasota Bradenton International Airport","lat":27.394631,"long":-82.554359},{"code":"STL","display":"STL - St. Louis Lambert International Airport","lat":38.748697,"long":-90.370003},{"code":"SYR","display":"SYR - Syracuse Hancock International Airport","lat":43.11119843,"long":-76.10630035},{"code":"TPA","display":"TPA - Tampa International Airport","lat":27.9755,"long":-82.533203},{"code":"TUL","display":"TUL - Tulsa International Airport","lat":36.19839859,"long":-95.88809967}]